CHANGES.md
COPYING
MANIFEST.in
README.md
README.rst
requirements.txt
screenshot.png
setup.py
ganymede/__init__.py
ganymede.egg-info/PKG-INFO
ganymede.egg-info/SOURCES.txt
ganymede.egg-info/dependency_links.txt
ganymede.egg-info/requires.txt
ganymede.egg-info/top_level.txt
ganymede/static/__init__.py
ganymede/static/ganymede.coffee
ganymede/static/ganymede.css
ganymede/static/jquery.ui.touch-punch.min.js
ganymede/static/__init__.py
ganymede/static/ganymede.css
ganymede/static/ganymede.js
ganymede/static/ganymede.svg
ganymede/static/jquery.ui.touch-punch.min.js
test/test_ganymede.py