Metadata-Version: 1.1
Name: ganymede
Version: 0.2.0.post1
Summary: Hacking Jupyter's atmosphere
Home-page: https://github.com/zimmermanncode/ganymede
Author: Stefan Zimmermann
Author-email: zimmermann.code@gmail.com
License: GPLv3
Keywords: ganymede,jupyter,ipython,notebook
Platform: UNKNOWN
Classifier: Development Status :: 3 - Alpha
Classifier: Intended Audience :: Developers
Classifier: License :: OSI Approved :: GNU General Public License (GPL)
Classifier: Operating System :: OS Independent
Classifier: Programming Language :: Python
Classifier: Programming Language :: Python :: 2
Classifier: Programming Language :: Python :: 2.7
Classifier: Programming Language :: Python :: 3
Classifier: Programming Language :: Python :: 3.3
Classifier: Programming Language :: Python :: 3.4
Classifier: Programming Language :: Python :: 3.5
Classifier: Programming Language :: JavaScript
Classifier: Topic :: Software Development
Classifier: Topic :: Utilities
